docketanalyzer_pipelines/__init__.py
docketanalyzer_pipelines/parallel_inference.py
docketanalyzer_pipelines/remote_pipeline.py
docketanalyzer_pipelines/pipelines/__init__.py
docketanalyzer_pipelines/pipelines/multilabel_pipelines.py
docketanalyzer_pipelines/pipelines/multitask_pipelines.py
docketanalyzer_pipelines/pipelines/ner_pipelines.py
docketanalyzer_pipelines/pipelines/pipeline.py
docketanalyzer_pipelines/routines/__init__.py
docketanalyzer_pipelines/routines/classification_routine.py
docketanalyzer_pipelines/routines/multilabel_classification_routine.py
docketanalyzer_pipelines/routines/multitask_routine.py
docketanalyzer_pipelines/routines/routine.py
docketanalyzer_pipelines/routines/token_classification_routine.py
docketanalyzer_pipelines-0.0.9.dist-info/LICENSE
docketanalyzer_pipelines-0.0.9.dist-info/METADATA
docketanalyzer_pipelines-0.0.9.dist-info/WHEEL
docketanalyzer_pipelines-0.0.9.dist-info/top_level.txt
docketanalyzer_pipelines-0.0.9.dist-info/RECORD
