Metadata-Version: 2.1
Name: docketanalyzer-pipelines
Version: 0.0.9
Summary: Inference pipelines and training routines extension for Docket Analyzer
Home-page: https://github.com/docketanalyzer/docketanalyzer
Author: Nathan Dahlberg
License-File: LICENSE
Requires-Dist: accelerate
Requires-Dist: datasets
Requires-Dist: docketanalyzer
Requires-Dist: scikit-learn
Requires-Dist: sentencepiece
Requires-Dist: tensorboard
Requires-Dist: torch
Requires-Dist: transformers
